Metadata-Version: 1.1
Name: flowvis
Version: 0.1.4
Summary: Visualization of flow on a transport network
Home-page: https://github.com/j-i-l/FlowVis
Author: Jonas I. Liechti
Author-email: jon.liechti@gmail.com
License: Apache 2.0
Download-URL: https://github.com/j-i-l/FlowVis/tarball/0.1.1
Keywords: visualization,network,transport,flow
Platform: UNKNOWN
Classifier: Development Status :: 3 - Alpha
Classifier: Intended Audience :: Developers
Classifier: Natural Language :: English
Classifier: License :: OSI Approved :: Apache Software License
Classifier: Programming Language :: Python
Classifier: Programming Language :: Python :: 2.7
Classifier: Operating System :: OS Independent
